convectors/__init__.py
convectors/base_layer.py
convectors/layers.py
convectors/models.py
convectors/utils.py
convectors/keras/__init__.py
convectors/keras/base.py
convectors/keras/callbacks.py
convectors/knn/__init__.py
convectors/knn/algorithms.py
convectors/merging/__init__.py
convectors/merging/concatenate.py
convectors/operations/__init__.py
convectors/operations/base.py
convectors/preprocessing/__init__.py
convectors/preprocessing/base.py
convectors/preprocessing/utils.py
convectors/reduction/__init__.py
convectors/reduction/base.py
convectors/tokenizers/__init__.py
convectors/tokenizers/base.py
convectors/tokenizers/stopwords.py
convectors/tokenizers/tiktoken.py
convectors/tokenizers/utils.py
convectors/vectorizers/__init__.py
convectors/vectorizers/bm25.py
convectors/vectorizers/bow.py
tests/__init__.py
tests/test_functional_api.py
tests/test_layers.py
tests/test_topics.py
convectors-1.0.1.dist-info/METADATA
convectors-1.0.1.dist-info/WHEEL
convectors-1.0.1.dist-info/top_level.txt
convectors-1.0.1.dist-info/RECORD
