Metadata-Version: 2.1
Name: convectors
Version: 1.0.1
Summary: NLP package
Home-page: https://github.com/kerighan/convectors
Author: Maixent Chenebaux
License: UNKNOWN
Platform: UNKNOWN
Classifier: Programming Language :: Python :: 3.8
Classifier: Operating System :: OS Independent
Requires-Dist: nltk >=3.8.1
Requires-Dist: numpy
Requires-Dist: scikit-learn
Requires-Dist: scipy
Requires-Dist: tqdm
Requires-Dist: pandas
Requires-Dist: dill
Requires-Dist: emoji
Requires-Dist: tiktoken
Requires-Dist: unidecode
